LICENSE.txt
README.md
setup.cfg
setup.py
Topsis_Vishavjeet_102003140/__init__.py
Topsis_Vishavjeet_102003140/topsis_102003140.py
Topsis_Vishavjeet_102003140.egg-info/PKG-INFO
Topsis_Vishavjeet_102003140.egg-info/SOURCES.txt
Topsis_Vishavjeet_102003140.egg-info/dependency_links.txt
Topsis_Vishavjeet_102003140.egg-info/requires.txt
Topsis_Vishavjeet_102003140.egg-info/top_level.txt